Workbook

Sheet Mode d'emploi
B1: Inventaire & plan de vente — collection de lithographies
B2: Environ 300 estampes signées et numérotées, 56 x 76 cm, en feuilles — Paris
B4: Comment utiliser ce classeur
B5: Onglet « Inventaire » | C5: Une ligne par ŒUVRE (pas par exemplaire). La colonne « Nb exemplaires » gère les doubles. Les cellules à remplir sont en jaune ; le reste se calcule tout seul.
B6: Onglet « Repères de prix » | C6: Prix réellement observés sur le marché (adjudications, annonces). À lire AVANT de fixer un prix cible.
B7: Onglet « Tableau de bord » | C7: Se met à jour seul. Donne le nombre de pièces par segment, la valeur cible et le net réellement encaissé.
B8: Onglet « Plan de vente » | C8: L'ordre des opérations, semaine par semaine.
B10: Les 3 segments (colonne R de l'Inventaire)
B11: A — Pièce forte | C11: Artiste coté, sujet recherché (musiciens, maternités, marines, cavaliers), exemplaire unique chez toi, petit tirage. Vente à l'unité, au prix fort, sans se presser.
B12: B — Courant | C12: Artiste connu mais sujet banal ou gros tirage (250-300). Vente à l'unité mais prix agressif, ou lots de 2-3.
B13: C — Volume / doubles | C13: Doubles, artistes non cotés, sujets difficiles. Lots de 5 à 20, ou cession en bloc à un marchand.
B15: Règles d'or
B16: Ne jamais inonder | C16: Ne mets JAMAIS deux exemplaires de la même image en ligne en même temps, ni 50 œuvres du même artiste la même semaine. Tu ferais chuter ton propre marché. Rythme : 5 à 10 annonces actives maximum.
B17: Prix plancher | C17: Fixe-le AVANT de publier et ne descends pas en dessous. Sinon tu négocieras dans le vide 300 fois.
B18: Test avant volume | C18: Vends d'abord 8-10 pièces représentatives. Les prix obtenus deviennent ta grille de référence pour les 290 autres.
B19: Jamais d'expertise payante | C19: Les sites « estimation gratuite » sont des apporteurs d'affaires. Une maison de ventes sérieuse estime gratuitement.
B21: Code couleur
B22: Fond jaune | C22: À remplir par toi.
B23: Texte bleu | C23: Valeur saisie à la main (hypothèse, prix décidé).
B24: Texte noir | C24: Formule — ne pas écraser.

Sheet Tableau de bord
B1: Tableau de bord
B2: Tout se calcule depuis l'onglet Inventaire. Rien à saisir ici.
B4: Volume
B5: Œuvres différentes référencées | C5: =COUNTA(Inventaire!$A$2:$A$401)
B6: Exemplaires au total (doubles inclus) | C6: =SUM(Inventaire!$O$2:$O$401)
B7: Photographiées et prêtes | C7: =COUNTIFS(Inventaire!$Q$2:$Q$401,"Oui")
B8: Vérifiées à la loupe (litho confirmée) | C8: =COUNTIFS(Inventaire!$R$2:$R$401,"Oui — litho")
B10: Répartition par segment | C10: Œuvres | D10: Exemplaires | E10: Valeur cible
B11: A — Pièces fortes | C11: =COUNTIFS(Inventaire!$S$2:$S$401,"A") | D11: =SUMIFS(Inventaire!$O$2:$O$401,Inventaire!$S$2:$S$401,"A") | E11: =SUMIFS(Inventaire!$V$2:$V$401,Inventaire!$S$2:$S$401,"A")
B12: B — Courant | C12: =COUNTIFS(Inventaire!$S$2:$S$401,"B") | D12: =SUMIFS(Inventaire!$O$2:$O$401,Inventaire!$S$2:$S$401,"B") | E12: =SUMIFS(Inventaire!$V$2:$V$401,Inventaire!$S$2:$S$401,"B")
B13: C — Volume / doubles | C13: =COUNTIFS(Inventaire!$S$2:$S$401,"C") | D13: =SUMIFS(Inventaire!$O$2:$O$401,Inventaire!$S$2:$S$401,"C") | E13: =SUMIFS(Inventaire!$V$2:$V$401,Inventaire!$S$2:$S$401,"C")
B14: Total | C14: =SUM(C11:C13) | D14: =SUM(D11:D13) | E14: =SUM(E11:E13)
B16: Avancement
B17: En ligne actuellement | C17: =COUNTIFS(Inventaire!$X$2:$X$401,"En ligne") | G17: Garde ce chiffre entre 5 et 10. Au-delà, tu casses tes propres prix.
B18: Vendues | C18: =COUNTIFS(Inventaire!$X$2:$X$401,"VENDUE")
B19: Invendues / retirées | C19: =COUNTIFS(Inventaire!$X$2:$X$401,"Invendue")+COUNTIFS(Inventaire!$X$2:$X$401,"Retirée")
B21: Argent
B22: Chiffre d'affaires brut | C22: =SUM(Inventaire!$Z$2:$Z$401)
B23: Frais et ports payés | C23: =SUM(Inventaire!$AA$2:$AA$401)
B24: Net réellement encaissé | C24: =SUM(Inventaire!$AB$2:$AB$401)
B25: Prix net moyen par pièce vendue | C25: =IFERROR(SUM(Inventaire!$AB$2:$AB$401)/COUNTIFS(Inventaire!$X$2:$X$401,"VENDUE"),0)
B26: Réalisé / valeur cible totale | C26: =IFERROR(C24/E14,0) | G26: Sous 60 %, tes prix cibles sont trop optimistes : révise-les.
B28: Seuil fiscal à surveiller (France)
B29: Ventes individuelles > 5 000 € | C29: =COUNTIFS(Inventaire!$Z$2:$Z$401,">5000") | G29: Au-delà de 5 000 € par cession : taxe forfaitaire de 6,5 % sur le prix de vente (ou option plus-value). En dessous : exonéré.
B30: Nombre de ventes sur l'année | C30: =COUNTIFS(Inventaire!$X$2:$X$401,"VENDUE") | G30: Au-delà de 30 ventes OU 2 000 € par plateforme et par an, la plateforme transmet tes données au fisc (DAC7). Ce n'est pas un impôt, mais anticipe-le.

Sheet Inventaire
A1: Réf | B1: Artiste | C1: Titre | D1: Année | E1: Éditeur / atelier | F1: Numérotation | G1: Tirage total | H1: Type d'épreuve | I1: Signé au crayon | J1: Dim. feuille (cm) | K1: Dim. image (cm) | L1: Papier | M1: Timbre sec / cachet | N1: Certificat | O1: Nb exemplaires | P1: État | Q1: Photo faite | R1: Litho vérifiée (loupe) | S1: Segment | T1: Prix plancher (€) | U1: Prix cible (€) | V1: Valeur cible stock (€) | W1: Canal prévu | X1: Statut | Y1: Date mise en ligne | Z1: Prix vendu (€) | AA1: Frais + port (€) | AB1: Net encaissé (€) | AC1: Plateforme / acheteur | AD1: Notes
A2: TOF-001 | B2: Louis Toffoli | C2: Le Bal musette | E2: Visions Nouvelles (à confirmer) | F2: 134/250 | G2: 250 | H2: Numérotée | I2: Oui | J2: 56 x 76 | N2: Oui | O2: 1 | P2: Neuf | Q2: Non | R2: À faire | S2: A | T2: 150 | U2: 320 | V2: =IFERROR(O2*U2,0) | W2: Enchères Drouot / eBay | X2: À photographier | AB2: =IFERROR(Z2-AA2,0) | AD2: Musiciens : sujet le plus recherché chez Toffoli. Annotation crayon en marge : « 204/10/151 ».
A3: TOF-002 | B3: Louis Toffoli | C3: (sans titre) — personnage à l'établi | E3: À confirmer | F3: à relever | H3: Numérotée | I3: Oui | J3: 56 x 76 | N3: Oui | O3: 1 | P3: Neuf | Q3: Non | R3: À faire | S3: B | T3: 90 | U3: 180 | V3: =IFERROR(O3*U3,0) | W3: eBay / Le Bon Coin | X3: À photographier | AB3: =IFERROR(Z3-AA3,0) | AD3: Relever la numérotation en bas à gauche.
A4: XXX-001 | B4: À IDENTIFIER | C4: Paysage pointilliste — cerisiers et reflets | E4: À confirmer | F4: 15/180 | G4: 180 | H4: Numérotée | I4: Oui | J4: 56 x 76 | L4: Vélin à bords barbés | N4: Oui | O4: 1 | P4: Neuf | Q4: Non | R4: À faire | S4: B | T4: 80 | U4: 200 | V4: =IFERROR(O4*U4,0) | W4: À déterminer | X4: À photographier | AB4: =IFERROR(Z4-AA4,0) | AD4: Signature en haut à gauche à déchiffrer — photo macro nécessaire.
A5: WEI-001 | B5: Claude Weisbuch | C5: (exemple à remplacer) | E5: Visions Nouvelles | F5: 72/150 | G5: 150 | H5: Numérotée | I5: Oui | J5: 56 x 76 | N5: Oui | O5: 2 | P5: Neuf | Q5: Non | R5: À faire | S5: B | T5: 80 | U5: 190 | V5: =IFERROR(O5*U5,0) | W5: Catawiki | X5: À photographier | AB5: =IFERROR(Z5-AA5,0) | AD5: LIGNE D'EXEMPLE — montre le format attendu. À supprimer ou remplacer.
V6: =IFERROR(O6*U6,0) | AB6: =IFERROR(Z6-AA6,0)
V7: =IFERROR(O7*U7,0) | AB7: =IFERROR(Z7-AA7,0)
V8: =IFERROR(O8*U8,0) | AB8: =IFERROR(Z8-AA8,0)
V9: =IFERROR(O9*U9,0) | AB9: =IFERROR(Z9-AA9,0)
V10: =IFERROR(O10*U10,0) | AB10: =IFERROR(Z10-AA10,0)
V11: =IFERROR(O11*U11,0) | AB11: =IFERROR(Z11-AA11,0)
V12: =IFERROR(O12*U12,0) | AB12: =IFERROR(Z12-AA12,0)
V13: =IFERROR(O13*U13,0) | AB13: =IFERROR(Z13-AA13,0)
V14: =IFERROR(O14*U14,0) | AB14: =IFERROR(Z14-AA14,0)
V15: =IFERROR(O15*U15,0) | AB15: =IFERROR(Z15-AA15,0)
V16: =IFERROR(O16*U16,0) | AB16: =IFERROR(Z16-AA16,0)
V17: =IFERROR(O17*U17,0) | AB17: =IFERROR(Z17-AA17,0)
... V401: =IFERROR(O401*U401,0) | AB401: =IFERROR(Z401-AA401,0)

Sheet Repères de prix
B1: Repères de prix observés
B2: Distinction capitale : un PRIX DEMANDÉ n'est pas un PRIX OBTENU. Les galeries affichent 400-1 200 € ; les enchères adjugent 50-250 €.
B4: Artiste | C4: Référence observée | D4: Type de prix | E4: Bas (€) | F4: Haut (€) | G4: Source
B5: Louis Toffoli | C5: « Maternité », litho couleurs 50x65, 53/150 | D5: ADJUGÉ (2021) | E5: 100 | F5: 100 | G5: mw-encheres.com — estimée 60-80 €, adjugée 100 €
B6: Louis Toffoli | C6: « Couple sur un banc », litho sur japon 50x73 | D6: Estimation salle (2023) | E6: 50 | F6: 100 | G6: richardmdv.com, vente du 12/12/2023
B7: Louis Toffoli | C7: Fourchette générale des estampes en salle | D7: Adjugé (marché) | E7: 30 | F7: 300 | G7: mr-expert.com / expertisez.com
B8: Louis Toffoli | C8: Annonces particuliers et galeries | D8: PRIX DEMANDÉ | E8: 120 | F8: 1090 | G8: leboncoin, eBay, passion-estampes
B9: Claude Weisbuch | C9: « Grande parade », litho signée BD | D9: Estimation salle (2025) | E9: 200 | F9: 300 | G9: primardeco.com
B10: Claude Weisbuch | C10: Fourchette générale des multiples | D10: Adjugé (marché) | E10: 30 | F10: 400 | G10: mr-expert.com
B11: Claude Weisbuch | C11: « Deux Cavaliers », litho signée /125 | D11: PRIX DEMANDÉ | E11: 487 | F11: 487 | G11: 1stdibs.com
B13: Ce que disent les experts du marché
B14: Toffoli | C14: « Très nombreuses sur le marché de l'art, la réelle valeur des estampes est aujourd'hui très faible. » — expertisez.com
B15: Weisbuch | C15: « La cote subit une tendance à la baisse et une désaffection des acquéreurs, car les estimations trop élevées ne trouvent pas d'acheteurs. » — mr-expert.com
B16: Conséquence | C16: Le prix affiché n'est pas le problème : c'est le prix auquel un acheteur clique. Vise le haut de la fourchette ADJUGÉE, pas le bas de la fourchette DEMANDÉE.
B19: Ce qui fait monter le prix
C20: • Petit tirage (moins de 150) plutôt que 250-300.
C21: • Sujet recherché : musiciens, maternités, marines, travailleurs pour Toffoli ; cavaliers, musiciens, théâtre pour Weisbuch.
C22: • Épreuve d'artiste (EA) ou hors commerce (HC) plutôt qu'un simple numéro.
C23: • Vraie lithographie sur pierre (grain irrégulier) plutôt qu'un offset signé.
C24: • Papier de qualité à bords barbés (Arches, BFK Rives) + timbre sec d'atelier.
C25: • État neuf, marges intactes, jamais encadré sous verre sans marie-louise.

Sheet Plan de vente
B1: Plan de vente — quelques heures par semaine
B2: Objectif : maximiser le prix. Horizon réaliste : 18 à 24 mois.
B4: Période | C4: Action | D4: Détail | E4: Fait ?
B5: Semaines 1-3 | C5: Inventaire complet | D5: Photographier et saisir les 300 pièces. 20 par séance. Pour chaque : vue entière + macro de la signature + macro de la numérotation. Fond blanc, lumière du jour, pas de flash.
B6: Semaine 2 | C6: Test loupe x10 | D6: Sur 10 pièces représentatives : grain irrégulier = vraie litho ; trame de points réguliers = offset. Décide du vocabulaire de tes annonces en conséquence.
B7: Semaine 3 | C7: Identifier les artistes manquants | D7: Photo macro de chaque signature illisible. Recouper avec les certificats d'authenticité et les bons de livraison de l'éditeur.
B8: Semaine 4 | C8: Segmentation A / B / C | D8: Croiser artiste + sujet + tirage + doubles. Vise environ 15 % en A, 45 % en B, 40 % en C.
B9: Semaines 5-8 | C9: Test de marché | D9: Mettre en vente 8 à 10 pièces seulement : 3 en enchères (Drouot Online / Interencheres), 3 sur eBay au prix cible, 3 sur Le Bon Coin en remise en main propre Paris. Noter les prix obtenus.
B10: Semaine 9 | C10: Recalibrer | D10: Réviser tous les prix cibles à partir des résultats réels. C'est ici que le tableau de bord sert.
B11: Mois 3-12 | C11: Écoulement du segment A puis B | D11: 5 à 10 annonces actives en permanence, jamais deux fois la même image. Renouveler chaque pièce vendue.
B12: Mois 3-24 | C12: Segment C en lots | D12: Lots thématiques de 5 à 20 sur eBay/Catawiki, ou cession en bloc à un marchand (compter 20-30 % du prix de détail, mais tout part d'un coup).
B13: En parallèle | C13: Consignation en salle | D13: Prendre rendez-vous avec 2-3 maisons parisiennes (Drouot, Millon, Lucien Paris, Richard). Estimation gratuite. Leur confier des lots groupés d'artistes secondaires.
B14: En continu | C14: Logistique | D14: Tubes rigides Ø10 cm et pochettes cristal. Pour du 56x76, la remise en main propre à Paris évite 15-25 € de port et les litiges pour pliure — privilégie-la.
B17: Comparatif des canaux
B18: Canal | C18: Frais vendeur | D18: Vitesse / effort | E18: Pour quel segment
B19: Le Bon Coin (Paris) | C19: 0 % | D19: Rapide, main propre, zéro port | E19: A et B — le meilleur rapport effort/net pour du 56x76
B20: eBay | C20: ~12 % + port | D20: Moyen, audience large | E20: A et B, et lots du segment C
B21: Catawiki | C21: ~12,5 % vendeur | D21: Lent (sélection), acheteurs internationaux | E21: A surtout — met en valeur les belles pièces
B22: Enchères en salle | C22: 15-25 % + frais | D22: Aucun effort, mais prix bas et invendus | E22: C et doubles, ou test de marché
B23: Marchand en gros | C23: 20-30 % du détail | D23: Immédiat, tout part | E23: C — la queue de collection
B24: Etsy | C24: ~9 % + port | D24: Lent, marché déco international | E24: B, sujets décoratifs
B25: Galerie en dépôt-vente | C25: 30-50 % | D25: Très lent | E25: A uniquement, si la galerie est spécialisée estampe
